setup.py
jyj758/__init__.py
jyj758/commonFunction.py
jyj758.egg-info/PKG-INFO
jyj758.egg-info/SOURCES.txt
jyj758.egg-info/dependency_links.txt
jyj758.egg-info/top_level.txt