Metadata-Version: 2.1
Name: jyj758
Version: 0.0.1
Summary: list calculation and so on
Home-page: 
Author: jungyongjun
Author-email: dydwns863@naver.com
License: MIT
Keywords: listsum
